inspire_matcher/__init__.py
inspire_matcher/api.py
inspire_matcher/config.py
inspire_matcher/core.py
inspire_matcher/ext.py
inspire_matcher/utils.py
inspire_matcher/validators.py
inspire_matcher-9.0.46.dist-info/licenses/LICENSE
inspire_matcher-9.0.46.dist-info/METADATA
inspire_matcher-9.0.46.dist-info/WHEEL
inspire_matcher-9.0.46.dist-info/entry_points.txt
inspire_matcher-9.0.46.dist-info/top_level.txt
inspire_matcher-9.0.46.dist-info/RECORD
